scikit_surgeryutils-2.1.0.dist-info/licenses/LICENSE
sksurgeryutils/__init__.py
sksurgeryutils/_version.py
sksurgeryutils/common_overlay_apps.py
sksurgeryutils/ui/__init__.py
sksurgeryutils/ui/sksurgerycharucotest_command_line.py
sksurgeryutils/ui/sksurgerycharucotest_demo.py
sksurgeryutils/ui/sksurgerymakecalibrationdots_command_line.py
sksurgeryutils/ui/sksurgerymakecalibrationdots_demo.py
sksurgeryutils/ui/sksurgeryrendermodelslikecamera_command_line.py
sksurgeryutils/ui/sksurgeryrendermodelslikecamera_demo.py
sksurgeryutils/ui/sksurgeryreslice_command_line.py
sksurgeryutils/ui/sksurgeryreslice_demo.py
sksurgeryutils/ui/sksurgerytextoverlay_command_line.py
sksurgeryutils/ui/sksurgerytextoverlay_demo.py
sksurgeryutils/ui/sksurgerytransformpolydata_command_line.py
sksurgeryutils/ui/sksurgerytransformpolydata_demo.py
sksurgeryutils/ui/sksurgeryvideocalibration_app.py
sksurgeryutils/ui/sksurgeryvideocalibration_command_line.py
sksurgeryutils/ui/sksurgeryvideocalibrationchecker_app.py
sksurgeryutils/ui/sksurgeryvideocalibrationchecker_command_line.py
sksurgeryutils/ui/sksurgeryvideolag_command_line.py
sksurgeryutils/ui/sksurgeryvideolag_demo.py
sksurgeryutils/utils/__init__.py
sksurgeryutils/utils/image_utils.py
sksurgeryutils/utils/opencv_video_capture_utils.py
sksurgeryutils/utils/screen_utils.py
scikit_surgeryutils-2.1.0.dist-info/METADATA
scikit_surgeryutils-2.1.0.dist-info/WHEEL
scikit_surgeryutils-2.1.0.dist-info/entry_points.txt
scikit_surgeryutils-2.1.0.dist-info/top_level.txt
scikit_surgeryutils-2.1.0.dist-info/RECORD
