Metadata-Version: 2.4
Name: scikit-surgeryutils
Version: 2.1.0
Summary: scikit-surgeryutils - Tests/demos utilities, based around opencv-contrib-python-headless and PySide6
Home-page: https://github.com/SciKit-Surgery/scikit-surgeryutils
Author: Matt Clarkson
Author-email: m.clarkson@ucl.ac.uk
License: BSD-3 license
Keywords: medical imaging
Classifier: Development Status :: 5 - Production/Stable
Classifier: Intended Audience :: Developers
Classifier: Intended Audience :: Healthcare Industry
Classifier: Intended Audience :: Information Technology
Classifier: Intended Audience :: Science/Research
Classifier: License :: OSI Approved :: BSD License
Classifier: Programming Language :: Python
Classifier: Programming Language :: Python :: 3.8
Classifier: Topic :: Scientific/Engineering :: Information Analysis
Classifier: Topic :: Scientific/Engineering :: Medical Science Apps.
License-File: LICENSE
Requires-Dist: numpy>=2.0.0
Requires-Dist: PySide6>=6.5.1.1
Requires-Dist: opencv-contrib-python-headless>=4.10.0.84
Requires-Dist: scikit-surgerycore>=0.1.7
Requires-Dist: scikit-surgeryimage>=1.0.0
Requires-Dist: scikit-surgeryvtk>=2.3.0
Requires-Dist: scikit-surgeryarucotracker>=1.1.0
Requires-Dist: scikit-surgerycalibration>=1.0.0
Dynamic: author
Dynamic: author-email
Dynamic: classifier
Dynamic: description
Dynamic: description-content-type
Dynamic: home-page
Dynamic: keywords
Dynamic: license
Dynamic: license-file
Dynamic: requires-dist
Dynamic: summary
